pyof/__init__.py
pyof/utils.py
pyof/foundation/__init__.py
pyof/foundation/base.py
pyof/foundation/basic_types.py
pyof/foundation/constants.py
pyof/foundation/exceptions.py
pyof/foundation/network_types.py
pyof/v0x01/__init__.py
pyof/v0x01/asynchronous/__init__.py
pyof/v0x01/asynchronous/error_msg.py
pyof/v0x01/asynchronous/flow_removed.py
pyof/v0x01/asynchronous/packet_in.py
pyof/v0x01/asynchronous/port_status.py
pyof/v0x01/common/__init__.py
pyof/v0x01/common/action.py
pyof/v0x01/common/constants.py
pyof/v0x01/common/flow_match.py
pyof/v0x01/common/header.py
pyof/v0x01/common/phy_port.py
pyof/v0x01/common/queue.py
pyof/v0x01/common/utils.py
pyof/v0x01/controller2switch/__init__.py
pyof/v0x01/controller2switch/barrier_reply.py
pyof/v0x01/controller2switch/barrier_request.py
pyof/v0x01/controller2switch/common.py
pyof/v0x01/controller2switch/features_reply.py
pyof/v0x01/controller2switch/features_request.py
pyof/v0x01/controller2switch/flow_mod.py
pyof/v0x01/controller2switch/get_config_reply.py
pyof/v0x01/controller2switch/get_config_request.py
pyof/v0x01/controller2switch/packet_out.py
pyof/v0x01/controller2switch/port_mod.py
pyof/v0x01/controller2switch/queue_get_config_reply.py
pyof/v0x01/controller2switch/queue_get_config_request.py
pyof/v0x01/controller2switch/set_config.py
pyof/v0x01/controller2switch/stats_reply.py
pyof/v0x01/controller2switch/stats_request.py
pyof/v0x01/symmetric/__init__.py
pyof/v0x01/symmetric/echo_reply.py
pyof/v0x01/symmetric/echo_request.py
pyof/v0x01/symmetric/hello.py
pyof/v0x01/symmetric/vendor_header.py
pyof/v0x04/__init__.py
pyof/v0x04/asynchronous/__init__.py
pyof/v0x04/asynchronous/error_msg.py
pyof/v0x04/asynchronous/flow_removed.py
pyof/v0x04/asynchronous/packet_in.py
pyof/v0x04/asynchronous/port_status.py
pyof/v0x04/common/__init__.py
pyof/v0x04/common/action.py
pyof/v0x04/common/constants.py
pyof/v0x04/common/flow_instructions.py
pyof/v0x04/common/flow_match.py
pyof/v0x04/common/header.py
pyof/v0x04/common/port.py
python_openflow-2021.1.dist-info/AUTHORS.rst
python_openflow-2021.1.dist-info/LICENSE
python_openflow-2021.1.dist-info/METADATA
python_openflow-2021.1.dist-info/WHEEL
python_openflow-2021.1.dist-info/top_level.txt
python_openflow-2021.1.dist-info/RECORD
