Metadata-Version: 2.1
Name: python-openflow
Version: 2021.1
Summary: Library to parse and generate OpenFlow messages
Home-page: http://github.com/kytos/python-openflow
Author: Kytos Team
Author-email: devel@lists.kytos.io
License: MIT
Platform: UNKNOWN
Classifier: License :: OSI Approved :: MIT License
Classifier: Operating System :: POSIX :: Linux
Classifier: Programming Language :: Python :: 3.6
Classifier: Programming Language :: Python :: 3.7
Classifier: Programming Language :: Python :: 3.8
Classifier: Programming Language :: Python :: 3.9
Classifier: Topic :: System :: Networking
Classifier: Topic :: Software Development :: Libraries
Provides-Extra: dev
Requires-Dist: pip-tools (>=2.0) ; extra == 'dev'
Requires-Dist: coverage ; extra == 'dev'
Requires-Dist: pytest ; extra == 'dev'
Requires-Dist: yala ; extra == 'dev'
Requires-Dist: tox ; extra == 'dev'
